jpdatetime/__init__.py
jpdatetime/jpdatetime.py
jpdatetime/kanji_to_num.py
jpdatetime/config/eras.json
test/__init__.py
test/test_jpdatetime.py
test/test_kanji_to_num.py
jpdatetime-1.5.0.dist-info/LICENSE
jpdatetime-1.5.0.dist-info/METADATA
jpdatetime-1.5.0.dist-info/WHEEL
jpdatetime-1.5.0.dist-info/top_level.txt
jpdatetime-1.5.0.dist-info/RECORD
