Metadata-Version: 2.1
Name: jpdatetime
Version: 1.5.0
Summary: The jpdatetime library extends Python's datetime to support Japanese eras (元号). It allows parsing and formatting dates in Japanese eras
Home-page: https://github.com/new-village/JapaneseDatetime
Author: new-village
License: Apache-2.0 license
License-File: LICENSE
